bsconf/__init__.py
bsconf/config.py
bsconf-0.0.2.dist-info/DESCRIPTION.rst
bsconf-0.0.2.dist-info/METADATA
bsconf-0.0.2.dist-info/RECORD
bsconf-0.0.2.dist-info/WHEEL
bsconf-0.0.2.dist-info/metadata.json
bsconf-0.0.2.dist-info/top_level.txt
