Metadata-Version: 2.0
Name: bsconf
Version: 0.0.2
Summary: library for reading config file of BS
Home-page: https://github.com/k0st1an/bsconf
Author: Konstantin Kruglov
Author-email: kruglovk@gmail.com
License: Apache License Version 2.0
Platform: UNKNOWN
Classifier: Development Status :: 3 - Alpha
Classifier: License :: OSI Approved :: Apache Software License
Classifier: Programming Language :: Python :: 3 :: Only
Classifier: Operating System :: POSIX :: Linux
